floating_point/ULA.v
module ULA(
    input reset,
    input clk,
    input[28:0] a,
    input[28:0] b,
    input sign_a, sign_b,
    input start,
    input op,
    output  [28:0] c,
    output reg done,
    output  reg sign_c 
);

parameter IDLE = 0, START = 1, SOMA = 2, MULT = 3, DONE = 4, TRATAR_MULT = 6;
wire [23:0]  multiplicador;
reg[23:0] multiplicador_efetivo;
wire [47:0] multiplicando; 
reg [4:0] counter;
reg [47:0] mult_result;
reg [28:0] soma_result;
reg [2:0] states;

assign multiplicando = (a > b) ? {24'b0, a[26:3]} : {24'b0, b[26:3]};
assign multiplicador = (a < b) ? {a[26:3]} : {b[26:3]};
assign c = !op ? soma_result : {1'b0,mult_result[47:21],1'b0};

always @* begin
    if(reset)
        states <= IDLE;
end

always @(posedge clk ) begin
    case (states)
        IDLE: begin
            if(start == 1)
                states <= START;
            else
                states <= IDLE;
        end

        START: begin
            if(op == 0)
                states <= SOMA;
            else
                states <= MULT;
        end

        SOMA: 
            states <= DONE;
        

        MULT: begin
            if(counter == 24)
                states <= DONE;
            else
                states <= MULT;
        end

        DONE:
            states <= DONE;

    endcase
end


always @(posedge clk) begin
    if(reset)
        states <= IDLE;

    case(states)
        IDLE:
            done <= 0;

        START: begin
            counter <= 0;
            mult_result <= 0;
        end

        SOMA: begin
            if(sign_a == sign_b) begin
                soma_result <= a + b;
                sign_c <= sign_a;
            end

            else begin
                soma_result <= b - a;
                sign_c <= sign_b;
            end
        end

        MULT: begin
            sign_c <= sign_a ^ sign_b;
            if (multiplicador[counter] == 1) begin
                mult_result <= mult_result + (multiplicando << counter);
            end
            counter <= counter + 1;
        end

        DONE:
            done <= 1;

    endcase
    
end


endmodule

floating_point/_testbenches/ULA_TB.v
module ULA_TB();

reg reset_tb;
reg clk_tb;
reg[28:0] a_tb;
reg[28:0] b_tb;
reg sign_a_tb, sign_b_tb;
reg start_tb;
reg op_tb;
wire[28:0] c_tb;
wire done_tb;
wire sign_c_tb; 

ULA UUT(
    .reset(reset_tb),
    .clk(clk_tb),
    .a(a_tb),
    .b(b_tb),
    .sign_a(sign_a_tb), 
    .sign_b(sign_b_tb),
    .start(start_tb),
    .op(op_tb),
    .c(c_tb),
    .done(done_tb),
    .sign_c(sign_c_tb) 
);


initial begin

$dumpfile("_testbenches/vvp/ULA_FLOAT.vcd");
$dumpvars(0, ULA_TB);
    clk_tb = 0;
    start_tb = 1;
    a_tb = {3'b000, 3'b111, 20'b0, 3'b0};
    b_tb = {3'b001, 4'b0, 19'b0, 3'b0};
    sign_a_tb = 0;
    sign_b_tb = 0;
    op_tb = 0;
    reset_tb = 0;

    #5
    reset_tb = 1;

    #5
    reset_tb = 0;
    #20
    start_tb = 0;
    
    #750
    $finish;
end

always #5
clk_tb = ~clk_tb;

endmodule

floating_point/_testbenches/vvp/ULA_FLOAT.vcd
$date
	Wed Jun 21 00:57:00 2023
$end
$version
	Icarus Verilog
$end
$timescale
	1s
$end
$scope module ULA_TB $end
$var wire 1 ! sign_c_tb $end
$var wire 1 " done_tb $end
$var wire 29 # c_tb [28:0] $end
$var reg 29 $ a_tb [28:0] $end
$var reg 29 % b_tb [28:0] $end
$var reg 1 & clk_tb $end
$var reg 1 ' op_tb $end
$var reg 1 ( reset_tb $end
$var reg 1 ) sign_a_tb $end
$var reg 1 * sign_b_tb $end
$var reg 1 + start_tb $end
$scope module UUT $end
$var wire 29 , a [28:0] $end
$var wire 29 - b [28:0] $end
$var wire 1 & clk $end
$var wire 1 ' op $end
$var wire 1 ( reset $end
$var wire 1 ) sign_a $end
$var wire 1 * sign_b $end
$var wire 1 + start $end
$var wire 48 . multiplicando [47:0] $end
$var wire 24 / multiplicador [23:0] $end
$var wire 29 0 c [28:0] $end
$var reg 5 1 counter [4:0] $end
$var reg 1 " done $end
$var reg 48 2 mult_result [47:0] $end
$var reg 1 ! sign_c $end
$var reg 29 3 soma_result [28:0] $end
$var reg 3 4 states [2:0] $end
$upscope $end
$upscope $end
$enddefinitions $end
#0
$dumpvars
bx 4
bx 3
bx 2
bx 1
bx 0
b11100000000000000000000 /
b100000000000000000000000 .
b100000000000000000000000000 -
b11100000000000000000000000 ,
1+
0*
0)
0(
0'
0&
b100000000000000000000000000 %
b11100000000000000000000000 $
bx #
x"
x!
$end
#5
b0 4
1&
1(
#10
0&
0(
#15
0"
b1 4
1&
#20
0&
#25
b10 4
b0 2
b0 1
1&
#30
0&
0+
#35
b111100000000000000000000000 #
b111100000000000000000000000 0
0!
b111100000000000000000000000 3
b100 4
1&
#40
0&
#45
1"
1&
