Processador/testeColeguinhaPepeThai/testeColeguinhaPepeThai/atrasa_clk_3x1.v
module atrasa_clk_3x1(
    input clk,
    output clk_out
);

reg[1:0] counter;
reg out;
assign clk_out = (counter == 0) ? 1 : 0;

initial begin
    counter <= 0;
end

always @(posedge clk ) begin
    if(counter == 2'b10)
        counter <= 2'b0;
    else
        counter <= counter + 1;
        
end




endmodule

Processador/testeColeguinhaPepeThai/testeColeguinhaPepeThai/_testbenches/atrasa_clk_3x1_tb.v
module atrasa_clk_3x1_tb();
reg clk_tb;
wire clk_out_tb;

atrasa_clk_3x1 uut(
    .clk(clk_tb),
    .clk_out(clk_out_tb)
);


initial begin
    $dumpfile("_testbenches/vvp/atrasaclk.vcd");
    $dumpvars(0, atrasa_clk_3x1_tb);

    clk_tb = 0;
    #100
    $finish;
end
always #5
clk_tb = ~clk_tb;







endmodule

Processador/testeColeguinhaPepeThai/testeColeguinhaPepeThai/_testbenches/vvp/atrasaclk.vcd
$date
	Thu Jun 08 09:12:30 2023
$end
$version
	Icarus Verilog
$end
$timescale
	1s
$end
$scope module atrasa_clk_3x1_tb $end
$var wire 1 ! clk_out_tb $end
$var reg 1 " clk_tb $end
$scope module uut $end
$var wire 1 " clk $end
$var wire 1 ! clk_out $end
$var reg 2 # counter [1:0] $end
$upscope $end
$upscope $end
$enddefinitions $end
#0
$dumpvars
b10 #
0"
0!
$end
#5
1!
b0 #
1"
#10
0"
#15
0!
b1 #
1"
#20
0"
#25
b10 #
1"
#30
0"
#35
1!
b0 #
1"
#40
0"
#45
0!
b1 #
1"
#50
0"
#55
b10 #
1"
#60
0"
#65
1!
b0 #
1"
#70
0"
#75
0!
b1 #
1"
#80
0"
#85
b10 #
1"
#90
0"
#95
1!
b0 #
1"
